{"v":1,"id":"N95AsH3n2KPbIwBGGpJk","createdAt":"2026-06-20T02:11:48.319Z","app":{"name":"AxiVale","version":"1.0.2"},"kind":"conversation","title":"how did harasho do in the last fight?","turns":[{"userText":"how did harasho do in the last fight?","agentText":"\n\nI’m checking the officer tool surface for the commander-review path and the AxiBridge identity/report tools, then I’ll pull Harasho’s most recent fight context and summarize the result.\n\nI found the officer namespace and I’m loading the command-review instructions first, then I’ll resolve Harasho and pull the latest run data rather than guessing from the rollup.\n\nHarasho resolves cleanly to `harasho.4281`. I’m listing recent runs now so I can isolate the latest one they led and review that fight instead of mixing in older nights.\n\nThe latest indexed fight was on `2026-06-18`, but Harasho was not the listed commander on that run. I’m switching to the player-level AxiBridge view so I can answer “how did Harasho do” for their own performance in the latest fight they appeared in.\n\nI have Harasho’s row from the latest run and his five-run baseline. I’m pulling his last few appearances now so I can say whether `2026-06-18` was above or below his own recent level rather than dropping raw totals without context.\n\nHarasho had a cleaner last fight than his recent norm: on the `2026-06-18` `Mesmer Kamoidra` run, he put up `7.41M` damage and `751.7k` down contribution on Tempest with only `1` death.\n\nThat run was `13` fights at `11-2` for the squad, and Harasho was `3rd` in total damage and `5th` in down contribution from the player rows in AxiBridge. Against his own last five logged runs (`2026-06-11` through `2026-06-18`), the damage was a bit below his recent average (`7.41M` vs `8.03M`), but the survivability was much better (`1` death vs `6.4` average). Cleanses were basically on baseline (`71` this run vs `73` average), while strips were low (`2` vs `9.4` average), which is not the main thing I’d grade a Tempest on anyway.\n\nNet: good fight, especially on survival. The squad winrate was strong that night, and Harasho stayed productive without feeding deaths.\n\nIf you meant “Harasho’s last fight as commander” rather than Harasho as a player, say that and I’ll pull only the runs he tagged.","filedAt":"7:10 PM","tools":[{"name":"load_skill"},{"name":"resolve_identity"},{"name":"axibridge_commander_stats","display":{"kind":"table","data":{"title":"Commanders","columns":[{"key":"account","label":"Commander"},{"key":"fightsLed","label":"Fights led"},{"key":"wins","label":"W"},{"key":"losses","label":"L"},{"key":"kdr","label":"KDR"},{"key":"deaths","label":"Deaths"}],"rows":[{"account":"harasho.4281","profession":"Troubadour","runs":19,"fightsLed":314,"wins":196,"losses":118,"kdr":1.29,"kills":5998,"deaths":100},{"account":"bro.2856","profession":"Troubadour","runs":10,"fightsLed":249,"wins":114,"losses":135,"kdr":0.72,"kills":3484,"deaths":133},{"account":"Jordan.1860","profession":"Troubadour","runs":9,"fightsLed":207,"wins":118,"losses":89,"kdr":1.16,"kills":3205,"deaths":80},{"account":"Ashtonlightstone.9145","profession":"Firebrand","runs":4,"fightsLed":84,"wins":65,"losses":19,"kdr":3.17,"kills":1571,"deaths":13},{"account":"VincentCross.1469","profession":"Firebrand","runs":1,"fightsLed":12,"wins":3,"losses":9,"kdr":0.25,"kills":29,"deaths":10},{"account":"Hassan Sabbah.1524","profession":"Troubadour","runs":5,"fightsLed":106,"wins":77,"losses":29,"kdr":1.67,"kills":2051,"deaths":28},{"account":"LightspeedJack.9473","profession":"Troubadour","runs":4,"fightsLed":45,"wins":22,"losses":23,"kdr":0.83,"kills":635,"deaths":24},{"account":"Fibbs.1623","profession":"Troubadour","runs":3,"fightsLed":53,"wins":35,"losses":18,"kdr":2.07,"kills":1365,"deaths":16},{"account":"VincentCross.1469","profession":"Renegade","runs":1,"fightsLed":24,"wins":17,"losses":7,"kdr":3.33,"kills":60,"deaths":1},{"account":"montezoma.5029","profession":"Firebrand","runs":1,"fightsLed":21,"wins":13,"losses":8,"kdr":1.49,"kills":61,"deaths":5},{"account":"undiee.3146","profession":"Troubadour","runs":1,"fightsLed":20,"wins":8,"losses":12,"kdr":0.5,"kills":37,"deaths":11},{"account":"Pentheus.4571","profession":"Firebrand","runs":1,"fightsLed":3,"wins":1,"losses":2,"kdr":0.34,"kills":24,"deaths":2},{"account":"harasho.4281","profession":"Berserker","runs":1,"fightsLed":1,"wins":1,"losses":0,"kdr":11.5,"kills":23,"deaths":0},{"account":"Jordan.1860","profession":"Troubadour","runs":9,"fightsLed":33,"wins":8,"losses":25,"kdr":1.03,"kills":756,"deaths":23},{"account":"harasho.4281","profession":"Troubadour","runs":5,"fightsLed":66,"wins":41,"losses":25,"kdr":0.91,"kills":829,"deaths":20},{"account":"bro.2856","profession":"Troubadour","runs":4,"fightsLed":65,"wins":34,"losses":31,"kdr":0.86,"kills":1127,"deaths":35},{"account":"LightspeedJack.9473","profession":"Troubadour","runs":4,"fightsLed":23,"wins":21,"losses":2,"kdr":5.8,"kills":760,"deaths":0},{"account":"Pentheus.4571","profession":"Spellbreaker","runs":3,"fightsLed":35,"wins":17,"losses":18,"kdr":1.3,"kills":395,"deaths":10},{"account":"Crunchy.6415","profession":"Scourge","runs":1,"fightsLed":6,"wins":3,"losses":3,"kdr":0.87,"kills":20,"deaths":3},{"account":"Ashtonlightstone.9145","profession":"Firebrand","runs":1,"fightsLed":1,"wins":1,"losses":0,"kdr":19,"kills":19,"deaths":0},{"account":"VincentCross.1469","profession":"Firebrand","runs":1,"fightsLed":1,"wins":1,"losses":0,"kdr":14,"kills":14,"deaths":0},{"account":"LightspeedJack.9473","profession":"Troubadour","runs":1,"fightsLed":20,"wins":19,"losses":1,"kdr":7.9,"kills":695,"deaths":0}]}}},{"name":"axibridge_repos_status","display":{"kind":"table","data":{"title":"Linked AxiBridge repos","columns":[{"key":"repo","label":"Repo"},{"key":"runs","label":"Runs"},{"key":"firstRun","label":"First run"},{"key":"lastRun","label":"Last run"},{"key":"cachedReports","label":"Cached"},{"key":"stale","label":"Live?"},{"key":"error","label":"Error"}],"rows":[{"repo":"gw2eww/fight-reports","runs":67,"firstRun":"2026-02-10T02:11:58.000Z","lastRun":"2026-06-19T00:59:22.000Z","cachedReports":67,"stale":"live","error":""},{"repo":"the-agg/alliance-fight-reports","runs":15,"firstRun":"2026-03-02T05:01:49.000Z","lastRun":"2026-06-06T02:13:43.000Z","cachedReports":15,"stale":"live","error":""},{"repo":"darkharasho/fight-reports-test","runs":201,"firstRun":"2026-01-25T19:07:45.000Z","lastRun":"2026-06-14T01:26:20.000Z","cachedReports":201,"stale":"live","error":""},{"repo":"darkharasho/fight-reports","runs":7,"firstRun":"2026-01-27T01:57:38.000Z","lastRun":"2026-02-08T20:12:38.000Z","cachedReports":7,"stale":"live","error":""},{"repo":"darkharasho/fight-reports-test-2","runs":33,"firstRun":"1970-01-21T11:41:29.100Z","lastRun":"2026-03-02T01:25:41.000Z","cachedReports":33,"stale":"live","error":""},{"repo":"gw2eww/fight-reports-test","runs":15,"firstRun":"2026-02-08T20:12:38.000Z","lastRun":"2026-02-16T06:43:09.581Z","cachedReports":15,"stale":"live","error":""}]}}},{"name":"axibridge_runs_list"},{"name":"axibridge_run_summary","display":{"kind":"table","data":{"title":"Mesmer Kamoidra — 11W/2L over 13 fights","columns":[{"key":"account","label":"Account"},{"key":"profession","label":"Profession"},{"key":"damage","label":"Damage"},{"key":"downContribution","label":"Down contrib"},{"key":"cleanses","label":"Cleanses"},{"key":"strips","label":"Strips"},{"key":"healing","label":"Healing"},{"key":"deaths","label":"Deaths"}],"rows":[{"account":"RedBeard.5743","profession":"Specter","damage":690323,"downContribution":58650,"cleanses":3109,"strips":9,"healing":3755359,"deaths":1,"downs":5},{"account":"Jordan.1860","profession":"Troubadour","damage":477809,"downContribution":53471,"cleanses":480,"strips":41,"healing":1487924,"deaths":1,"downs":3},{"account":"Fibbs.1623","profession":"Dragonhunter","damage":768470,"downContribution":88972,"cleanses":1024,"strips":9,"healing":862324,"deaths":1,"downs":4},{"account":"Kaliptuce.9051","profession":"Firebrand","damage":2015698,"downContribution":207247,"cleanses":138,"strips":34,"healing":30916,"deaths":2,"downs":8},{"account":"Wisdom.6028","profession":"Reaper","damage":5506881,"downContribution":695103,"cleanses":139,"strips":649,"healing":56452,"deaths":1,"downs":8},{"account":"Brotalist.3085","profession":"Berserker","damage":8061929,"downContribution":1587227,"cleanses":98,"strips":13,"healing":5775,"deaths":1,"downs":7},{"account":"Oceanomega.4856","profession":"Troubadour","damage":301985,"downContribution":10708,"cleanses":404,"strips":2,"healing":609685,"deaths":3,"downs":4},{"account":"undiee.3146","profession":"Druid","damage":258392,"downContribution":17747,"cleanses":3288,"strips":13,"healing":7125462,"deaths":1,"downs":1},{"account":"Raven Paradox.1860","profession":"Reaper","damage":5350118,"downContribution":737473,"cleanses":147,"strips":833,"healing":156,"deaths":2,"downs":6},{"account":"btran.9183","profession":"Firebrand","damage":2596111,"downContribution":302229,"cleanses":343,"strips":8,"healing":79264,"deaths":1,"downs":2},{"account":"BreakN.5496","profession":"Berserker","damage":8900976,"downContribution":1618400,"cleanses":145,"strips":4,"healing":273281,"deaths":0,"downs":5},{"account":"RoguExile.4735","profession":"Firebrand","damage":2811488,"downContribution":311195,"cleanses":361,"strips":1,"healing":153250,"deaths":1,"downs":2},{"account":"Sunny.3891","profession":"Druid","damage":689081,"downContribution":41519,"cleanses":967,"strips":5,"healing":2024256,"deaths":4,"downs":9},{"account":"Jax Blake.7250","profession":"Harbinger","damage":784942,"downContribution":89522,"cleanses":142,"strips":699,"healing":1361964,"deaths":1,"downs":1},{"account":"Arx.9785","profession":"Druid","damage":298013,"downContribution":18390,"cleanses":2533,"strips":2,"healing":4948564,"deaths":0,"downs":1},{"account":"Beornin.5793","profession":"Troubadour","damage":641004,"downContribution":73981,"cleanses":1574,"strips":16,"healing":3268584,"deaths":1,"downs":4},{"account":"VincentCross.1469","profession":"Tempest","damage":5914250,"downContribution":728947,"cleanses":213,"strips":3,"healing":77153,"deaths":2,"downs":6},{"account":"General Moo.7930","profession":"Reaper","damage":4667428,"downContribution":574480,"cleanses":189,"strips":501,"healing":17062,"deaths":3,"downs":6},{"account":"Vettexl.9726","profession":"Firebrand","damage":5064596,"downContribution":598296,"cleanses":240,"strips":6,"healing":442536,"deaths":1,"downs":1},{"account":"sbr.8170","profession":"Firebrand","damage":2967384,"downContribution":316918,"cleanses":176,"strips":4,"healing":294336,"deaths":1,"downs":3},{"account":"Bouzouki.7598","profession":"Druid","damage":222621,"downContribution":13099,"cleanses":2302,"strips":0,"healing":3412471,"deaths":1,"downs":4},{"account":"Stan.9684","profession":"Troubadour","damage":90064,"downContribution":9153,"cleanses":369,"strips":1,"healing":914253,"deaths":1,"downs":1},{"account":"harasho.4281","profession":"Tempest","damage":7412553,"downContribution":751708,"cleanses":71,"strips":2,"healing":97148,"deaths":1,"downs":3},{"account":"pillo.9341","profession":"Tempest","damage":463680,"downContribution":62838,"cleanses":55,"strips":0,"healing":33466,"deaths":0,"downs":0},{"account":"Endless.4325","profession":"Reaper","damage":2462578,"downContribution":246816,"cleanses":169,"strips":188,"healing":2386,"deaths":5,"downs":9},{"account":"Grimmster.6924","profession":"Druid","damage":334991,"downContribution":18358,"cleanses":1312,"strips":3,"healing":3036202,"deaths":1,"downs":5},{"account":"Izathel.4058","profession":"Tempest","damage":5203584,"downContribution":581286,"cleanses":81,"strips":5,"healing":138615,"deaths":2,"downs":9},{"account":"IronOre.7826","profession":"Firebrand","damage":1619970,"downContribution":195008,"cleanses":419,"strips":1,"healing":268959,"deaths":1,"downs":2},{"account":"Hostile Pudding.5617","profession":"Berserker","damage":1708671,"downContribution":306576,"cleanses":311,"strips":7,"healing":449387,"deaths":0,"downs":1},{"account":"Scone Expenditures.1097","profession":"Tempest","damage":31602,"downContribution":702,"cleanses":206,"strips":0,"healing":444079,"deaths":0,"downs":1},{"account":"hotep.8715","profession":"Troubadour","damage":148393,"downContribution":10493,"cleanses":249,"strips":1,"healing":582994,"deaths":4,"downs":5},{"account":"red armadillo.4593","profession":"Firebrand","damage":1432327,"downContribution":141185,"cleanses":98,"strips":4,"healing":220264,"deaths":3,"downs":3},{"account":"Tomatuyucom.8469","profession":"Troubadour","damage":103343,"downContribution":14257,"cleanses":455,"strips":2,"healing":736115,"deaths":1,"downs":1},{"account":"pinguinox.9528","profession":"Troubadour","damage":232534,"downContribution":25431,"cleanses":1165,"strips":15,"healing":956988,"deaths":2,"downs":4},{"account":"Tysun.5092","profession":"Troubadour","damage":483486,"downContribution":49164,"cleanses":1318,"strips":21,"healing":2706859,"deaths":0,"downs":0},{"account":"Voyl.5241","profession":"Troubadour","damage":469588,"downContribution":43541,"cleanses":1088,"strips":10,"healing":2696775,"deaths":2,"downs":3},{"account":"iNicooo.9587","profession":"Reaper","damage":5022248,"downContribution":830881,"cleanses":58,"strips":524,"healing":388,"deaths":3,"downs":5},{"account":"FatherHyperion.1047","profession":"Firebrand","damage":62227,"downContribution":6386,"cleanses":72,"strips":0,"healing":241262,"deaths":1,"downs":1},{"account":"Eliare.4069","profession":"Druid","damage":233530,"downContribution":14229,"cleanses":1923,"strips":7,"healing":4466004,"deaths":1,"downs":6},{"account":"Genki.3125","profession":"Troubadour","damage":499716,"downContribution":54404,"cleanses":1537,"strips":16,"healing":2975414,"deaths":2,"downs":2},{"account":"AMINE.5278","profession":"Necromancer","damage":5516412,"downContribution":752567,"cleanses":89,"strips":1346,"healing":81182,"deaths":2,"downs":6}]}}},{"name":"axibridge_player_stats","display":{"kind":"table","data":{"title":"Player stats","columns":[{"key":"account","label":"Account"},{"key":"runs","label":"Runs"},{"key":"dps","label":"DPS"},{"key":"cleanses","label":"Cleanses"},{"key":"strips","label":"Strips"},{"key":"healing","label":"Healing"},{"key":"deaths","label":"Deaths"},{"key":"combatHours","label":"Combat h"}],"rows":[{"account":"harasho.4281","runs":5,"dps":2724,"damage":40145617,"cleanses":367,"strips":47,"healing":833277,"deaths":32,"combatHours":4.1,"professions":"Tempest, Amalgam, Luminary, Berserker, Spellbreaker, Troubadour","lastSeen":"2026-06-19T02:39:40.000Z"}]}}},{"name":"axibridge_query","display":{"kind":"table","data":{"title":"Query result","columns":[{"key":"run_id","label":"run_id"},{"key":"date","label":"date"},{"key":"title","label":"title"},{"key":"profession","label":"profession"},{"key":"damage","label":"damage"},{"key":"downContribution","label":"downContribution"},{"key":"cleanses","label":"cleanses"},{"key":"strips","label":"strips"},{"key":"healing","label":"healing"},{"key":"deaths","label":"deaths"},{"key":"downs","label":"downs"},{"key":"fights","label":"fights"},{"key":"squadDeaths","label":"squadDeaths"},{"key":"wins","label":"wins"},{"key":"losses","label":"losses"}],"rows":[{"run_id":"20260611-180811-zq6c","date":"","title":"","profession":"Tempest","damage":6916849,"downContribution":1161827,"cleanses":38,"strips":0,"healing":11161,"deaths":4,"downs":10,"fights":"","squadDeaths":"","wins":"","losses":""},{"run_id":"20260613-180943-doi9","date":"","title":"","profession":"Tempest","damage":6391061,"downContribution":554461,"cleanses":42,"strips":4,"healing":230073,"deaths":9,"downs":17,"fights":"","squadDeaths":"","wins":"","losses":""},{"run_id":"20260613-182620-kqul","date":"","title":"","profession":"Tempest","damage":10058742,"downContribution":964506,"cleanses":109,"strips":40,"healing":329054,"deaths":13,"downs":25,"fights":"","squadDeaths":"","wins":"","losses":""},{"run_id":"20260615-180311-lj8b","date":"","title":"","profession":"Tempest","damage":9366412,"downContribution":1036512,"cleanses":107,"strips":1,"healing":165841,"deaths":5,"downs":10,"fights":"","squadDeaths":"","wins":"","losses":""},{"run_id":"20260618-175922-yasl","date":"","title":"","profession":"Tempest","damage":7412553,"downContribution":751708,"cleanses":71,"strips":2,"healing":97148,"deaths":1,"downs":3,"fights":"","squadDeaths":"","wins":"","losses":""}]}}}]}]}